Workbook

Sheet Consolidated Edison Inc.
A2: In this spreadsheet, we estimate the stock price of Consolidated Edison for 2026 with (a) constant-growth model and (b) P/E ratio.

Sheet Hist. Price & RRR
A1: Date | B1: Stock Close | C1: ED Return | E1: S&P 500 Close
A2: 43172 | B2: =VLOOKUP(A2,[1]HD_price_daily!$A$8:$B$1768,2,0) -> 178.35 | E2: =VLOOKUP(A2,'[1]S&P500_DAILY'!$A$8:$B$1768,2,0) -> 2765.31
A3: 43173 | B3: =VLOOKUP(A3,[1]HD_price_daily!$A$8:$B$1768,2,0) -> 177.41 | C3: =B3/B2-1 -> -0.0052705355 | D3: =_xlfn.FORMULATEXT(C3) -> =B3/B2-1 | E3: =VLOOKUP(A3,'[1]S&P500_DAILY'!$A$8:$B$1768,2,0) -> 2749.48 | F3: =E3/E2-1 -> -0.0057244938 | G3: =_xlfn.FORMULATEXT(F3) -> =E3/E2-1
A4: 43174 | B4: =VLOOKUP(A4,[1]HD_price_daily!$A$8:$B$1768,2,0) -> 178.07 | C4: =B4/B3-1 -> 0.0037201962 | D4: =_xlfn.FORMULATEXT(C4) -> =B4/B3-1 | E4: =VLOOKUP(A4,'[1]S&P500_DAILY'!$A$8:$B$1768,2,0) -> 2747.33 | F4: =E4/E3-1 -> -0.00078196604 | G4: =_xlfn.FORMULATEXT(F4) -> =E4/E3-1
A5: 43175 | B5: =VLOOKUP(A5,[1]HD_price_daily!$A$8:$B$1768,2,0) -> 178.96 | C5: =B5/B4-1 -> 0.0049980345 | D5: =_xlfn.FORMULATEXT(C5) -> =B5/B4-1 | E5: =VLOOKUP(A5,'[1]S&P500_DAILY'!$A$8:$B$1768,2,0) -> 2752.01 | F5: =E5/E4-1 -> 0.0017034721 | G5: =_xlfn.FORMULATEXT(F5) -> =E5/E4-1
A6: 43178 | B6: =VLOOKUP(A6,[1]HD_price_daily!$A$8:$B$1768,2,0) -> 177.1 | C6: =B6/B5-1 -> -0.010393384 | D6: =_xlfn.FORMULATEXT(C6) -> =B6/B5-1 | E6: =VLOOKUP(A6,'[1]S&P500_DAILY'!$A$8:$B$1768,2,0) -> 2712.92 | F6: =E6/E5-1 -> -0.014204164 | G6: =_xlfn.FORMULATEXT(F6) -> =E6/E5-1 | I6: Risk-free rate: | J6: 0.0437
A7: 43179 | B7: =VLOOKUP(A7,[1]HD_price_daily!$A$8:$B$1768,2,0) -> 178.16 | C7: =B7/B6-1 -> 0.005985319 | D7: =_xlfn.FORMULATEXT(C7) -> =B7/B6-1 | E7: =VLOOKUP(A7,'[1]S&P500_DAILY'!$A$8:$B$1768,2,0) -> 2716.94 | F7: =E7/E6-1 -> 0.0014817982 | G7: =_xlfn.FORMULATEXT(F7) -> =E7/E6-1 | I7: Beta: (slope function) | J7: =SLOPE(C3:C1762,F3:F1762) -> 0.98120688 | K7: =_xlfn.FORMULATEXT(J7) -> =SLOPE(C3:C1762,F3:F1762) | L7: =_xlfn.COVARIANCE.P($C$3:$C$1762,$F$3:$F$1762)/_xlfn.VAR.P($F$3:$F$1762) -> 0.98120688
A8: 43180 | B8: =VLOOKUP(A8,[1]HD_price_daily!$A$8:$B$1768,2,0) -> 178.02 | C8: =B8/B7-1 -> -0.00078581051 | D8: =_xlfn.FORMULATEXT(C8) -> =B8/B7-1 | E8: =VLOOKUP(A8,'[1]S&P500_DAILY'!$A$8:$B$1768,2,0) -> 2711.93 | F8: =E8/E7-1 -> -0.0018439862 | G8: =_xlfn.FORMULATEXT(F8) -> =E8/E7-1 | I8: Average annual return of market | J8: =(1+AVERAGE(F3:F1762))^252-1 -> 0.12568607 | K8: =_xlfn.FORMULATEXT(J8) -> =(1+AVERAGE(F3:F1762))^252-1
A9: 43181 | B9: =VLOOKUP(A9,[1]HD_price_daily!$A$8:$B$1768,2,0) -> 175.29 | C9: =B9/B8-1 -> -0.015335356 | D9: =_xlfn.FORMULATEXT(C9) -> =B9/B8-1 | E9: =VLOOKUP(A9,'[1]S&P500_DAILY'!$A$8:$B$1768,2,0) -> 2643.69 | F9: =E9/E8-1 -> -0.025162891 | G9: =_xlfn.FORMULATEXT(F9) -> =E9/E8-1 | I9: Required Rate of Return (CAPM) | J9: =J6+J7*(J8-J6) -> 0.1241453 | K9: =_xlfn.FORMULATEXT(J9) -> =J6+J7*(J8-J6)
A10: 43182 | B10: =VLOOKUP(A10,[1]HD_price_daily!$A$8:$B$1768,2,0) -> 171.8 | C10: =B10/B9-1 -> -0.019909864 | D10: =_xlfn.FORMULATEXT(C10) -> =B10/B9-1 | E10: =VLOOKUP(A10,'[1]S&P500_DAILY'!$A$8:$B$1768,2,0) -> 2588.26 | F10: =E10/E9-1 -> -0.020966906 | G10: =_xlfn.FORMULATEXT(F10) -> =E10/E9-1
A11: 43185 | B11: =VLOOKUP(A11,[1]HD_price_daily!$A$8:$B$1768,2,0) -> 176.38 | C11: =B11/B10-1 -> 0.026658906 | D11: =_xlfn.FORMULATEXT(C11) -> =B11/B10-1 | E11: =VLOOKUP(A11,'[1]S&P500_DAILY'!$A$8:$B$1768,2,0) -> 2658.55 | F11: =E11/E10-1 -> 0.027157241 | G11: =_xlfn.FORMULATEXT(F11) -> =E11/E10-1 | I11: average daily return
A12: 43186 | B12: =VLOOKUP(A12,[1]HD_price_daily!$A$8:$B$1768,2,0) -> 174.68 | C12: =B12/B11-1 -> -0.009638281 | D12: =_xlfn.FORMULATEXT(C12) -> =B12/B11-1 | E12: =VLOOKUP(A12,'[1]S&P500_DAILY'!$A$8:$B$1768,2,0) -> 2612.62 | F12: =E12/E11-1 -> -0.017276335 | G12: =_xlfn.FORMULATEXT(F12) -> =E12/E11-1
A13: 43187 | B13: =VLOOKUP(A13,[1]HD_price_daily!$A$8:$B$1768,2,0) -> 174.76 | C13: =B13/B12-1 -> 0.00045798031 | D13: =_xlfn.FORMULATEXT(C13) -> =B13/B12-1 | E13: =VLOOKUP(A13,'[1]S&P500_DAILY'!$A$8:$B$1768,2,0) -> 2605 | F13: =E13/E12-1 -> -0.0029166124 | G13: =_xlfn.FORMULATEXT(F13) -> =E13/E12-1
A14: 43188 | B14: =VLOOKUP(A14,[1]HD_price_daily!$A$8:$B$1768,2,0) -> 178.24 | C14: =B14/B13-1 -> 0.019913024 | D14: =_xlfn.FORMULATEXT(C14) -> =B14/B13-1 | E14: =VLOOKUP(A14,'[1]S&P500_DAILY'!$A$8:$B$1768,2,0) -> 2640.87 | F14: =E14/E13-1 -> 0.013769674 | G14: =_xlfn.FORMULATEXT(F14) -> =E14/E13-1
A15: 43192 | B15: =VLOOKUP(A15,[1]HD_price_daily!$A$8:$B$1768,2,0) -> 172.9 | C15: =B15/B14-1 -> -0.029959605 | D15: =_xlfn.FORMULATEXT(C15) -> =B15/B14-1 | E15: =VLOOKUP(A15,'[1]S&P500_DAILY'!$A$8:$B$1768,2,0) -> 2581.88 | F15: =E15/E14-1 -> -0.022337336 | G15: =_xlfn.FORMULATEXT(F15) -> =E15/E14-1
A16: 43193 | B16: =VLOOKUP(A16,[1]HD_price_daily!$A$8:$B$1768,2,0) -> 173.76 | C16: =B16/B15-1 -> 0.0049739734 | D16: =_xlfn.FORMULATEXT(C16) -> =B16/B15-1 | E16: =VLOOKUP(A16,'[1]S&P500_DAILY'!$A$8:$B$1768,2,0) -> 2614.45 | F16: =E16/E15-1 -> 0.012614839 | G16: =_xlfn.FORMULATEXT(F16) -> =E16/E15-1
A17: 43194 | B17: =VLOOKUP(A17,[1]HD_price_daily!$A$8:$B$1768,2,0) -> 177.44 | C17: =B17/B16-1 -> 0.021178637 | D17: =_xlfn.FORMULATEXT(C17) -> =B17/B16-1 | E17: =VLOOKUP(A17,'[1]S&P500_DAILY'!$A$8:$B$1768,2,0) -> 2644.69 | F17: =E17/E16-1 -> 0.011566486 | G17: =_xlfn.FORMULATEXT(F17) -> =E17/E16-1
A18: 43195 | B18: =VLOOKUP(A18,[1]HD_price_daily!$A$8:$B$1768,2,0) -> 179.13 | C18: =B18/B17-1 -> 0.0095243463 | D18: =_xlfn.FORMULATEXT(C18) -> =B18/B17-1 | E18: =VLOOKUP(A18,'[1]S&P500_DAILY'!$A$8:$B$1768,2,0) -> 2662.84 | F18: =E18/E17-1 -> 0.0068628081 | G18: =_xlfn.FORMULATEXT(F18) -> =E18/E17-1
A19: 43196 | B19: =VLOOKUP(A19,[1]HD_price_daily!$A$8:$B$1768,2,0) -> 174.45 | C19: =B19/B18-1 -> -0.026126277 | D19: =_xlfn.FORMULATEXT(C19) -> =B19/B18-1 | E19: =VLOOKUP(A19,'[1]S&P500_DAILY'!$A$8:$B$1768,2,0) -> 2604.47 | F19: =E19/E18-1 -> -0.021920205 | G19: =_xlfn.FORMULATEXT(F19) -> =E19/E18-1
A20: 43199 | B20: =VLOOKUP(A20,[1]HD_price_daily!$A$8:$B$1768,2,0) -> 172.51 | C20: =B20/B19-1 -> -0.011120665 | D20: =_xlfn.FORMULATEXT(C20) -> =B20/B19-1 | E20: =VLOOKUP(A20,'[1]S&P500_DAILY'!$A$8:$B$1768,2,0) -> 2613.16 | F20: =E20/E19-1 -> 0.0033365714 | G20: =_xlfn.FORMULATEXT(F20) -> =E20/E19-1
A21: 43200 | B21: =VLOOKUP(A21,[1]HD_price_daily!$A$8:$B$1768,2,0) -> 173.49 | C21: =B21/B20-1 -> 0.0056808301 | D21: =_xlfn.FORMULATEXT(C21) -> =B21/B20-1 | E21: =VLOOKUP(A21,'[1]S&P500_DAILY'!$A$8:$B$1768,2,0) -> 2656.87 | F21: =E21/E20-1 -> 0.016726875 | G21: =_xlfn.FORMULATEXT(F21) -> =E21/E20-1
A22: 43201 | B22: =VLOOKUP(A22,[1]HD_price_daily!$A$8:$B$1768,2,0) -> 172.86 | C22: =B22/B21-1 -> -0.0036313332 | D22: =_xlfn.FORMULATEXT(C22) -> =B22/B21-1 | E22: =VLOOKUP(A22,'[1]S&P500_DAILY'!$A$8:$B$1768,2,0) -> 2642.19 | F22: =E22/E21-1 -> -0.0055252986 | G22: =_xlfn.FORMULATEXT(F22) -> =E22/E21-1
A23: 43202 | B23: =VLOOKUP(A23,[1]HD_price_daily!$A$8:$B$1768,2,0) -> 173.36 | C23: =B23/B22-1 -> 0.0028925142 | D23: =_xlfn.FORMULATEXT(C23) -> =B23/B22-1 | E23: =VLOOKUP(A23,'[1]S&P500_DAILY'!$A$8:$B$1768,2,0) -> 2663.99 | F23: =E23/E22-1 -> 0.0082507314 | G23: =_xlfn.FORMULATEXT(F23) -> =E23/E22-1
... A1762: 45729 | B1762: =VLOOKUP(A1762,[1]HD_price_daily!$A$8:$B$1768,2,0) -> 347.25 | C1762: =B1762/B1761-1 -> -0.047925863 | D1762: =_xlfn.FORMULATEXT(C1762) -> =B1762/B1761-1 | E1762: =VLOOKUP(A1762,'[1]S&P500_DAILY'!$A$8:$B$1768,2,0) -> 5521.52 | F1762: =E1762/E1761-1 -> -0.013891022 | G1762: =_xlfn.FORMULATEXT(F1762) -> =E1762/E1761-1

Sheet Dividends and Growth Rate
A1: Date | B1: Dividends | C1: Year | E1: Year | F1: Annual dividned per share (DPS) | I1: Annaul Dividend Growth Rate
A2: 43150 | B2: 1.03 | C2: 2018 | E2: 2018 | F2: =SUMIF($C$2:$C$29,E2,$B$2:$B$29) -> 4.12 | G2: =_xlfn.FORMULATEXT(F2) -> =SUMIF($C$2:$C$29,E2,$B$2:$B$29)
A3: 43237 | B3: 1.03 | C3: 2018 | E3: 2019 | F3: =SUMIF($C$2:$C$29,E3,$B$2:$B$29) -> 5.44 | G3: =_xlfn.FORMULATEXT(F3) -> =SUMIF($C$2:$C$29,E3,$B$2:$B$29) | I3: =(F8/F6)^(1/(E8-E6))-1 -> 0.088214375 | J3: =_xlfn.FORMULATEXT(I3) -> =(F8/F6)^(1/(E8-E6))-1
A4: 43328 | B4: 1.03 | C4: 2018 | E4: 2020 | F4: =SUMIF($C$2:$C$29,E4,$B$2:$B$29) -> 6 | G4: =_xlfn.FORMULATEXT(F4) -> =SUMIF($C$2:$C$29,E4,$B$2:$B$29)
A5: 43419 | B5: 1.03 | C5: 2018 | E5: 2021 | F5: =SUMIF($C$2:$C$29,E5,$B$2:$B$29) -> 6.6 | G5: =_xlfn.FORMULATEXT(F5) -> =SUMIF($C$2:$C$29,E5,$B$2:$B$29)
A6: 43522 | B6: 1.36 | C6: 2019 | E6: 2022 | F6: =SUMIF($C$2:$C$29,E6,$B$2:$B$29) -> 7.6 | G6: =_xlfn.FORMULATEXT(F6) -> =SUMIF($C$2:$C$29,E6,$B$2:$B$29)
A7: 43608 | B7: 1.36 | C7: 2019 | E7: 2023 | F7: =SUMIF($C$2:$C$29,E7,$B$2:$B$29) -> 8.36 | G7: =_xlfn.FORMULATEXT(F7) -> =SUMIF($C$2:$C$29,E7,$B$2:$B$29)
A8: 43699 | B8: 1.36 | C8: 2019 | E8: 2024 | F8: =SUMIF($C$2:$C$29,E8,$B$2:$B$29) -> 9 | G8: =_xlfn.FORMULATEXT(F8) -> =SUMIF($C$2:$C$29,E8,$B$2:$B$29) | I8: =F8/F7-1 -> 0.076555024
A9: 43790 | B9: 1.36 | C9: 2019
A10: 43886 | B10: 1.5 | C10: 2020
A11: 43970 | B11: 1.5 | C11: 2020
A12: 44061 | B12: 1.5 | C12: 2020
A13: 44154 | B13: 1.5 | C13: 2020
A14: 44250 | B14: 1.65 | C14: 2021
A15: 44336 | B15: 1.65 | C15: 2021
A16: 44427 | B16: 1.65 | C16: 2021
A17: 44518 | B17: 1.65 | C17: 2021
A18: 44614 | B18: 1.9 | C18: 2022
A19: 44700 | B19: 1.9 | C19: 2022
A20: 44791 | B20: 1.9 | C20: 2022
... A29: 45610 | B29: 2.25 | C29: 2024
E57: Data Source: Yahoo! Finance

Sheet Leverage Ratio
B1: Date | C1: Total Debt | D1: Total Equity | E1: Total Asset | F1: Leverage Ratio
B2: 44561 | C2: 43488000 | D2: =E2-C2 -> 33042000 | E2: 76530000 | F2: =C2/E2 -> 0.56824775 | G2: =_xlfn.FORMULATEXT(F2) -> =C2/E2
B3: 44926 | C3: 46467000 | D3: =E3-C3 -> 29978000 | E3: 76445000 | F3: =C3/E3 -> 0.60784878 | G3: =_xlfn.FORMULATEXT(F3) -> =C3/E3
B4: 45291 | C4: 50595000 | D4: =E4-C4 -> 21281000 | E4: 71876000 | F4: =C4/E4 -> 0.70392064 | G4: =_xlfn.FORMULATEXT(F4) -> =C4/E4
B5: 45657 | C5: 52511000 | D5: =E5-C5 -> 18070000 | E5: 70581000 | F5: =C5/E5 -> 0.74398209 | G5: =_xlfn.FORMULATEXT(F5) -> =C5/E5
C9: Data Source: Yahoo! Finance

Sheet P-E ratio and Earning
A1: Date | B1: PE CURRENT Ratio
A2: 44564 | B2: 27.33 | D2: Average CURRENT P/E Ratio | E2: =AVERAGE(B2:B40) -> 21.566667 | F2: =_xlfn.FORMULATEXT(E2) -> =AVERAGE(B2:B40)
A3: 44593 | B3: 23.76
A4: 44621 | B4: 20.64
A5: 44652 | B5: 19.17 | E5: Estimated Earning 2026 | F5: 15.06
A6: 44683 | B6: 19.49
A7: 44713 | B7: 18.87
A8: 44743 | B8: 17.72
A9: 44774 | B9: 18.79 | E9: Data Source: Yahoo! Finance
A10: 44805 | B10: 18.03
A11: 44837 | B11: 17.43
A12: 44866 | B12: 17.84
A13: 44896 | B13: 19.71
A14: 44929 | B14: 19.04
A15: 44958 | B15: 19.67
A16: 44986 | B16: 17.43
A17: 45019 | B17: 17.85
A18: 45047 | B18: 18.14
A19: 45078 | B19: 17.57
A20: 45110 | B20: 18.89
A21: 45139 | B21: 20.74
... A40: 45719 | B40: 26.12
A62: Data Source: macrotrends.net

Sheet Price Esimation
A2: Constant-growth model
B3: Dividend per share in 2024 | C3: ='Dividends and Growth Rate'!F8 -> 9 | D3: =_xlfn.FORMULATEXT(C3) -> ='Dividends and Growth Rate'!F8
B4: Required Rate of Return | C4: ='Hist. Price & RRR'!J9 -> 0.1241453 | D4: =_xlfn.FORMULATEXT(C4) -> ='Hist. Price & RRR'!J9
B5: Annual dividend growth rate | C5: ='Dividends and Growth Rate'!I3 -> 0.088214375 | D5: =_xlfn.FORMULATEXT(C5) -> ='Dividends and Growth Rate'!I3
B7: Projected dividend for 2027 | C7: =C3*(1+C5)^3 -> 11.598074 | D7: =_xlfn.FORMULATEXT(C7) -> =C3*(1+C5)^3
B8: Value of the stock in 2026 using Constant Growth Model | C8: =C7/(C4-C5) -> 322.78811 | D8: =_xlfn.FORMULATEXT(C8) -> =C7/(C4-C5)
E13: 0
A21: P/E ratio
B22: Trailing Average P/E Ratio | C22: ='P-E ratio and Earning'!E2 -> 21.566667 | D22: =_xlfn.FORMULATEXT(C22) -> ='P-E ratio and Earning'!E2
B23: Earning Estimate 2025 | C23: ='P-E ratio and Earning'!F5 -> 15.06 | D23: =_xlfn.FORMULATEXT(C23) -> ='P-E ratio and Earning'!F5
B25: Value of the stock in 2026 using P/E ratio | C25: =C22*C23 -> 324.794 | D25: =_xlfn.FORMULATEXT(C25) -> =C22*C23
